posts/__init__.py
posts/posts.py
posts-0.2.2.dist-info/DESCRIPTION.rst
posts-0.2.2.dist-info/METADATA
posts-0.2.2.dist-info/metadata.json
posts-0.2.2.dist-info/RECORD
posts-0.2.2.dist-info/top_level.txt
posts-0.2.2.dist-info/WHEEL
