Metadata-Version: 2.0
Name: posts
Version: 0.2.2
Summary: A Python library for send mail easily
Home-page: https://github.com/importcjj/Post
Author: Jiaju.Chen
Author-email: jiaju.chen@ele.me
License: BSD2
Platform: UNKNOWN
